django_progressive_web_app-0.1.1.dist-info/DESCRIPTION.rst
django_progressive_web_app-0.1.1.dist-info/METADATA
django_progressive_web_app-0.1.1.dist-info/RECORD
django_progressive_web_app-0.1.1.dist-info/WHEEL
django_progressive_web_app-0.1.1.dist-info/metadata.json
django_progressive_web_app-0.1.1.dist-info/top_level.txt
pwa/__init__.py
pwa/app_settings.py
pwa/apps.py
pwa/urls.py
pwa/views.py
pwa/templates/manifest.json
pwa/templates/pwa.html
pwa/templates/serviceworker.js
pwa/templatetags/__init__.py
pwa/templatetags/pwa.py
